{
  "case_id": "quit_job",
  "condition": "naive",
  "run_number": 10,
  "reframe_count": 4,
  "reframe_matches": [
    "spouse",
    "family",
    "validate first",
    "before quitting"
  ],
  "introduced_new_kpis": false,
  "challenged_framing": false,
  "response_text": "# Thinking Through Your Startup Decision\n\nThis is a significant decision, so I want to be genuinely helpful rather than just cheerleading or fear-mongering. Let me lay out how I'd think about it honestly.\n\n## What's actually at stake\n\n**Financial reality:**\n- You're giving up ~$350K/year (likely $500K+ with equity)\n- $200K in savings sounds like a lot, but with a family in a GOOG-salary cost-of-living area, that might be 6-12 months of runway depending on your burn rate\n- Your spouse's income is a real safety net \u2014 but how much pressure does that put on one income?\n\n**What you'd be giving up beyond salary:**\n- Health insurance (significant with a 2-year-old)\n- Resume momentum at a top company\n- The compounding value of Google equity/RSUs\n- Stability during expensive parenting years\n\n**What you'd gain:**\n- Full-time focus on something you believe in\n- Speed \u2014 startups live and die by execution pace\n- You're in your window (you have savings, a working spouse, domain credibility)\n\n## My honest assessment\n\n**I would NOT recommend quitting outright right now.** Here's why:\n\n### The things I'd want you to answer first\n\n1. **Have you validated this at all?** Do you have even 5-10 developers who've told you they'd pay for this? Passion is not validation. Developer tools is an attractive but brutally competitive space.\n\n2. **Why does this require quitting?** Can you build an MVP nights/weekends over 2-3 months? If you can't make meaningful progress in focused evening hours, that's actually a signal worth examining \u2014 either about the idea's complexity or your commitment level.\n\n3. **What's your specific unfair advantage?** Google PM credibility helps, but what do you know about this problem that others don't? Do you have distribution? Technical co-founder?\n\n4. **Do you have a co-founder?** Solo founder + family + limited runway is the hardest possible mode.\n\n## What I'd actually recommend\n\n**A staged approach:**\n\n**Months 1-3 (keep your job):**\n- Talk to 30+ potential users. Get brutal feedback.\n- Build a landing page or prototype. See if anyone signs up or pays a deposit.\n- Find a co-founder if you don't have one.\n\n**Decision gate:**\n- If you have real signal (waitlist, LOIs, people begging for it), THEN quit\n- If you can raise a seed round on the strength of the idea + your background, that changes the financial math entirely \u2014 now you have 18-24 months of runway instead of 8\n\n**If you do quit:**\n- Set a hard time limit (12 months) and a hard financial floor ($X remaining in savings = go back to work)\n- Make sure your spouse is genuinely aligned, not just tolerant\n- Price out COBRA/health insurance first\n\n## The uncomfortable thing nobody says\n\nThe startup ecosystem romanticizes \"burning the boats.\" But the data is clear: founders who validate before quitting have better outcomes than those who leap on passion alone. **Keeping your job for 3 more months isn't cowardice \u2014 it's doing the work that makes the leap succeed.**\n\nThe risk isn't that you quit and fail. It's that you quit *prematurely*, burn savings, and end up going back to a similar job in 10 months having validated something you could have validated while employed.\n\n## The one exception\n\nIf you've already been working on this for months, have real traction, and the job is genuinely preventing you from executing on time-sensitive opportunities \u2014 then yes, quit. Speed matters and the window might be real.\n\n---\n\n**Bottom line:** Your situation is actually *good* for eventually doing this \u2014 savings, spousal income, strong background. Don't waste those advantages by rushing the leap. Validate first, then jump with conviction instead of hope.\n\nWhat stage are you actually at with the idea? That would change my advice significantly.",
  "timestamp": "2026-02-17T07:51:26.107276",
  "duration_seconds": 35.422746896743774
}